shakepy/__init__.py
shakepy/py.typed
shakepy-0.1.0.dist-info/WHEEL
shakepy-0.1.0.dist-info/METADATA
shakepy-0.1.0.dist-info/RECORD
