Metadata-Version: 2.3
Name: shakepy
Version: 0.1.0
Summary: A Shakepay API Interface for Python 
Author: quizque
Author-email: quizque <13785390+quizque@users.noreply.github.com>
Requires-Python: >=3.14
